{"operationalLayers":[{"id":"Accidental_Deaths_8938","layerType":"ArcGISFeatureLayer","url":"https://services.arcgis.com/V6ZHFr6zdgNZuVG0/arcgis/rest/services/Accidental_Deaths/FeatureServer/0","visibility":true,"opacity":0.8,"title":"Accidental Deaths","itemId":"11afe7ebbd2e405aa2a2554a103686c8","layerDefinition":{"drawingInfo":{"renderer":{"visualVariables":[{"type":"sizeInfo","field":"Deaths","valueUnit":"unknown","minSize":6,"maxSize":37.5,"minDataValue":2814,"maxDataValue":121179},{"type":"colorInfo","field":"U_C_Rate","stops":[{"value":52,"color":[0,66,56,255],"label":"< 52"},{"value":58,"color":[128,161,156,255],"label":null},{"value":64.2,"color":[255,255,255,255],"label":"64.2"},{"value":70,"color":[210,153,139,255],"label":null},{"value":76,"color":[165,50,23,255],"label":"> 76"}]}],"authoringInfo":{"visualVariables":[{"type":"sizeInfo","minSliderValue":2814,"maxSliderValue":121179},{"type":"colorInfo","minSliderValue":38.56775011,"maxSliderValue":93.91913541,"theme":"above-and-below"}]},"type":"classBreaks","field":"U_C_Rate","minValue":-9007199254740991,"classBreakInfos":[{"symbol":{"color":[227,139,79,255],"size":9,"angle":0,"xoffset":0,"yoffset":0,"type":"esriSMS","style":"esriSMSCircle","outline":{"color":[255,255,255,178],"width":0.75,"type":"esriSLS","style":"esriSLSSolid"}},"classMaxValue":9007199254740991}]}}},"popupInfo":{"title":"Accidental_Deaths","fieldInfos":[{"fieldName":"ST","label":"ST","isEditable":true,"tooltip":"","visible":true,"stringFieldOption":"textbox","isEditableOnLayer":true},{"fieldName":"StateFIPS","label":"StateFIPS","isEditable":true,"tooltip":"","visible":true,"format":{"places":0,"digitSeparator":true},"stringFieldOption":"textbox","isEditableOnLayer":true},{"fieldName":"Population","label":"Population","isEditable":true,"tooltip":"","visible":true,"format":{"places":0,"digitSeparator":true},"stringFieldOption":"textbox","isEditableOnLayer":true},{"fieldName":"Deaths","label":"Accidental Deaths","isEditable":true,"tooltip":"","visible":true,"format":{"places":0,"digitSeparator":true},"stringFieldOption":"textbox","isEditableOnLayer":true},{"fieldName":"U_C_Rate","label":"Accidental Deaths per 100,000","isEditable":true,"tooltip":"","visible":true,"format":{"places":2,"digitSeparator":true},"stringFieldOption":"textbox","isEditableOnLayer":true},{"fieldName":"FID","label":"FID","isEditable":false,"tooltip":"","visible":true,"format":{"places":0,"digitSeparator":true},"stringFieldOption":"textbox","isEditableOnLayer":false}],"description":null,"showAttachments":true,"mediaInfos":[]}}],"baseMap":{"baseMapLayers":[{"id":"VectorTile_1970","type":"VectorTileLayer","layerType":"VectorTileLayer","title":"Light Gray Base","styleUrl":"https://cdn.arcgis.com/sharing/rest/content/items/291da5eab3a0412593b66d384379f89f/resources/styles/root.json","visibility":true,"opacity":1},{"id":"VectorTile_7117","type":"VectorTileLayer","layerType":"VectorTileLayer","title":"Light Gray Reference","styleUrl":"https://cdn.arcgis.com/sharing/rest/content/items/1768e8369a214dfab4e2167d5c5f2454/resources/styles/root.json","isReference":true,"visibility":true,"opacity":1}],"title":"Light Gray Canvas"},"spatialReference":{"wkid":102100,"latestWkid":3857},"authoringApp":"WebMapViewer","authoringAppVersion":"8.2","version":"2.17"}